freemailchecker/__init__.py
freemailchecker/freemailchecker.py
freemailchecker/data/freemaildomains.csv
freemailchecker-0.1.1.dist-info/LICENSE
freemailchecker-0.1.1.dist-info/METADATA
freemailchecker-0.1.1.dist-info/WHEEL
freemailchecker-0.1.1.dist-info/top_level.txt
freemailchecker-0.1.1.dist-info/RECORD
