Metadata-Version: 2.1
Name: freemailchecker
Version: 0.1.1
Summary: A simple python package which checks for the domain in a list of free and disposable email domains. Includes gmail.com and mailinator.com style
Home-page: https://github.com/pjr/freemailchecker
Author: Philip Reynolds
Author-email: philip.reynolds@gmail.com
Requires-Python: >=3.6
License-File: LICENSE
Requires-Dist: importlib-resources ; python_version < "3.9"
